{
  "timestamp": "2026-01-31 23:56:57",
  "experiment_name": "ablation_full",
  "checkpoint_path": "./outputs/checkpoints/best_model_ablation_full.pth",
  "artifacts_dir": "./outputs/results/artifacts_ablation_full",
  "best_val_loss": 0.0011178935616044327,
  "best_epoch": 1,
  "val_metrics": {
    "mse": 0.0011012908071279526,
    "mae": 0.02479964680969715,
    "rmse": 0.033185701847752935,
    "r2": -0.9552180767059326,
    "directional_accuracy": 0.4838693262772237,
    "ic": -0.013722318182557185,
    "rank_ic": -0.01079451324389256
  },
  "test_metrics": {
    "mse": 0.0010637638624757528,
    "mae": 0.027053285390138626,
    "rmse": 0.03261539302960725,
    "r2": -1.6438653469085693,
    "directional_accuracy": 0.5017651059063544,
    "ic": 0.00023203877925302634,
    "rank_ic": 0.0037722603054758425,
    "icir": 0.0017181939977452864,
    "rank_icir": 0.029287259905348074,
    "n_test_samples": 199988,
    "n_test_days": 692
  },
  "config": {
    "batch_size": 1024,
    "lr": 0.001,
    "epochs": 30,
    "n_embd": 64,
    "n_layers": 2,
    "gnn_embd": 32,
    "seq_len": 60,
    "train_start": "2018-01-01",
    "train_end": "2020-06-30",
    "val_start": "2020-07-01",
    "val_end": "2020-12-31",
    "test_start": "2021-01-01",
    "test_end": "2023-12-31",
    "profile": "paper",
    "output_dir": "./outputs",
    "checkpoint_name": "best_model_ablation_full.pth",
    "use_graph": true,
    "temporal_backend": "rwkv"
  },
  "loss_log": "./outputs/logs/training_losses_ablation_full.json"
}